{
  "names": [
    "フシギダネ",
    "フシギソウ",
    "フシギバナ",
    "ヒトカゲ",
    "リザード",
    "リザードン",
    "ゼニガメ",
    "カメール",
    "カメックス",
    "キャタピー",
    "トランセル",
    "バタフリー",
    "コラッタ",
    "ラッタ",
    "アーボ",
    "アーボック",
    "ピカチュウ",
    "ライチュウ",
    "サンド",
    "サンドパン",
    "ピッピ",
    "ピクシー",
    "ロコン",
    "キュウコン",
    "プリン",
    "プクリン",
    "ディグダ",
    "ダグドリオ",
    "ニャース",
    "ペルシアン",
    "コダック",
    "ゴルダック",
    "マンキー",
    "オコリザル",
    "ガーディ",
    "ウインディ",
    "マタツボミ",
    "ウツドン",
    "ウツボット",
    "イシツブテ",
    "ゴローン",
    "ゴローニャ",
    "ヤドン",
    "ヤドラン",
    "コイル",
    "レアコイル",
    "カモネギ",
    "ドードー",
    "ドードリオ",
    "ゴース",
    "ゴースト",
    "ゲンガー",
    "イワーク",
    "カラカラ",
    "ガラガラ",
    "ラッキー",
    "ガルーラ",
    "バリヤード",
    "カイロス",
    "メタモン",
    "イーブイ",
    "シャワーズ",
    "サンダース",
    "ブースター",
    "ミニリュウ",
    "ハクリュー",
    "カイリュー",
    "ミュウ",
    "チコリータ",
    "ベイリーフ",
    "メガニウム",
    "ヒノアラシ",
    "マグマラシ",
    "バクフーン",
    "ワニノコ",
    "アリゲイツ",
    "オーダイル",
    "ピチュー",
    "ピィ",
    "ププリン",
    "トゲピー",
    "トゲチック",
    "ネイティ",
    "ネイティオ",
    "メリープ",
    "モココ",
    "デンリュウ",
    "ウソッキー",
    "ウパー",
    "ヌオー",
    "エーフィ",
    "ブラッキー",
    "ヤミカラス",
    "ヤドキング",
    "ソーナンス",
    "ハガネール",
    "ツボツボ",
    "ヘラクロス",
    "ニューラ",
    "デリバード",
    "デルビル",
    "ヘルガー",
    "ハピナス",
    "ライコウ",
    "エンテイ",
    "スイクン",
    "ヨーギラス",
    "サナギラス",
    "バンギラス",
    "キモリ",
    "ジュプトル",
    "ジュカイン",
    "アチャモ",
    "ワカシャモ",
    "バシャーモ",
    "ミズゴロウ",
    "ヌマクロー",
    "ラグラージ",
    "ラルトス",
    "キルリア",
    "サーナイト",
    "ナマケロ",
    "ヤルキモノ",
    "ケッキング",
    "ヤミラミ",
    "クチート",
    "ココドラ",
    "コドラ",
    "ボスゴドラ",
    "プラスル",
    "マイナン",
    "ゴクリン",
    "マルノーム",
    "ナックラー",
    "ビブラーバ",
    "フライゴン",
    "チルット",
    "チルタリス",
    "カゲボウズ",
    "ジュペッタ",
    "アブソル",
    "ソーナノ",
    "タマザラシ",
    "トドクラー",
    "トドゼルガ",
    "タツベイ",
    "コモルー",
    "ボーマンダ",
    "ラティアス",
    "ラティオス",
    "ナエトル",
    "ハヤシガメ",
    "ドダイトス",
    "ヒコザル",
    "モウカザル",
    "ゴウカザル",
    "ポッチャマ",
    "ポッタイシ",
    "エンペルト",
    "コリンク",
    "ルクシオ",
    "レントラー",
    "フワンテ",
    "フワライド",
    "ドンカラス",
    "ウソハチ",
    "マネネ",
    "ピンプク",
    "ミカルゲ",
    "リオル",
    "ルカリオ",
    "グレッグル",
    "ドクロッグ",
    "ユキカブリ",
    "ユキノオー",
    "マニューラ",
    "ジバコイル",
    "トゲキッス",
    "リーフィア",
    "グレイシア",
    "エルレイド",
    "クレセリア",
    "ダークライ",
    "ムンナ",
    "ムシャーナ",
    "イシズマイ",
    "イワパレス",
    "ワシボン",
    "ウォーグル",
    "チゴラス",
    "ガチゴラス",
    "ニンフィア",
    "デデンネ",
    "バケッチャ",
    "パンプジン",
    "オンバット",
    "オンバーン",
    "アゴジムシ",
    "デンヂムシ",
    "クワガノン",
    "アブリー",
    "アブリボン",
    "ヌイコグマ",
    "キテルグマ",
    "キュワワー",
    "トゲデマル",
    "ミミッキュ",
    "ジジーロン",
    "ウッウ",
    "エレズン",
    "ストリンダー",
    "ニャオハ",
    "ニャローテ",
    "マスカーニャ",
    "ホゲータ",
    "アチゲータ",
    "ラウドボーン",
    "クワッス",
    "ウェルカモ",
    "ウェーニバル",
    "パモ",
    "パモット",
    "パーモット",
    "アルクジラ",
    "ハルクジラ",
    "ドオー"
  ],
  "typeMap": {
    "フシギダネ": "うとうと",
    "フシギソウ": "うとうと",
    "フシギバナ": "うとうと",
    "ヒトカゲ": "すやすや",
    "リザード": "すやすや",
    "リザードン": "すやすや",
    "ゼニガメ": "ぐっすり",
    "カメール": "ぐっすり",
    "カメックス": "ぐっすり",
    "キャタピー": "うとうと",
    "トランセル": "うとうと",
    "バタフリー": "うとうと",
    "コラッタ": "すやすや",
    "ラッタ": "すやすや",
    "アーボ": "うとうと",
    "アーボック": "うとうと",
    "ピカチュウ": "すやすや",
    "ライチュウ": "すやすや",
    "サンド": "ぐっすり",
    "サンドパン": "ぐっすり",
    "ピッピ": "すやすや",
    "ピクシー": "すやすや",
    "ロコン": "すやすや",
    "キュウコン": "すやすや",
    "プリン": "すやすや",
    "プクリン": "すやすや",
    "ディグダ": "すやすや",
    "ダグドリオ": "すやすや",
    "ニャース": "すやすや",
    "ペルシアン": "すやすや",
    "コダック": "うとうと",
    "ゴルダック": "ぐっすり",
    "マンキー": "うとうと",
    "オコリザル": "うとうと",
    "ガーディ": "すやすや",
    "ウインディ": "すやすや",
    "マタツボミ": "うとうと",
    "ウツドン": "うとうと",
    "ウツボット": "うとうと",
    "イシツブテ": "ぐっすり",
    "ゴローン": "ぐっすり",
    "ゴローニャ": "ぐっすり",
    "ヤドン": "すやすや",
    "ヤドラン": "すやすや",
    "コイル": "ぐっすり",
    "レアコイル": "ぐっすり",
    "カモネギ": "ぐっすり",
    "ドードー": "ぐっすり",
    "ドードリオ": "ぐっすり",
    "ゴース": "うとうと",
    "ゴースト": "うとうと",
    "ゲンガー": "うとうと",
    "イワーク": "ぐっすり",
    "カラカラ": "ぐっすり",
    "ガラガラ": "ぐっすり",
    "ラッキー": "すやすや",
    "ガルーラ": "すやすや",
    "バリヤード": "すやすや",
    "カイロス": "うとうと",
    "メタモン": "すやすや",
    "イーブイ": "すやすや",
    "シャワーズ": "ぐっすり",
    "サンダース": "すやすや",
    "ブースター": "すやすや",
    "ミニリュウ": "うとうと",
    "ハクリュー": "うとうと",
    "カイリュー": "うとうと",
    "ミュウ": "すやすや",
    "チコリータ": "うとうと",
    "ベイリーフ": "うとうと",
    "メガニウム": "うとうと",
    "ヒノアラシ": "すやすや",
    "マグマラシ": "すやすや",
    "バクフーン": "すやすや",
    "ワニノコ": "ぐっすり",
    "アリゲイツ": "ぐっすり",
    "オーダイル": "ぐっすり",
    "ピチュー": "ぐっすり",
    "ピィ": "ぐっすり",
    "ププリン": "ぐっすり",
    "トゲピー": "ぐっすり",
    "トゲチック": "すやすや",
    "ネイティ": "すやすや",
    "ネイティオ": "すやすや",
    "メリープ": "すやすや",
    "モココ": "すやすや",
    "デンリュウ": "すやすや",
    "ウソッキー": "ぐっすり",
    "ウパー": "ぐっすり",
    "ヌオー": "ぐっすり",
    "エーフィ": "すやすや",
    "ブラッキー": "うとうと",
    "ヤミカラス": "うとうと",
    "ヤドキング": "すやすや",
    "ソーナンス": "すやすや",
    "ハガネール": "ぐっすり",
    "ツボツボ": "うとうと",
    "ヘラクロス": "うとうと",
    "ニューラ": "うとうと",
    "デリバード": "うとうと",
    "デルビル": "うとうと",
    "ヘルガー": "うとうと",
    "ハピナス": "すやすや",
    "ライコウ": "すやすや",
    "エンテイ": "すやすや",
    "スイクン": "ぐっすり",
    "ヨーギラス": "ぐっすり",
    "サナギラス": "ぐっすり",
    "バンギラス": "うとうと",
    "キモリ": "うとうと",
    "ジュプトル": "うとうと",
    "ジュカイン": "うとうと",
    "アチャモ": "すやすや",
    "ワカシャモ": "ぐっすり",
    "バシャーモ": "ぐっすり",
    "ミズゴロウ": "ぐっすり",
    "ヌマクロー": "ぐっすり",
    "ラグラージ": "ぐっすり",
    "ラルトス": "すやすや",
    "キルリア": "すやすや",
    "サーナイト": "すやすや",
    "ナマケロ": "すやすや",
    "ヤルキモノ": "うとうと",
    "ケッキング": "すやすや",
    "ヤミラミ": "うとうと",
    "クチート": "ぐっすり",
    "ココドラ": "ぐっすり",
    "コドラ": "ぐっすり",
    "ボスゴドラ": "ぐっすり",
    "プラスル": "すやすや",
    "マイナン": "すやすや",
    "ゴクリン": "うとうと",
    "マルノーム": "うとうと",
    "ナックラー": "ぐっすり",
    "ビブラーバ": "ぐっすり",
    "フライゴン": "ぐっすり",
    "チルット": "ぐっすり",
    "チルタリス": "うとうと",
    "カゲボウズ": "うとうと",
    "ジュペッタ": "うとうと",
    "アブソル": "うとうと",
    "ソーナノ": "ぐっすり",
    "タマザラシ": "ぐっすり",
    "トドクラー": "ぐっすり",
    "トドゼルガ": "ぐっすり",
    "タツベイ": "うとうと",
    "コモルー": "うとうと",
    "ボーマンダ": "うとうと",
    "ラティアス": "うとうと",
    "ラティオス": "うとうと",
    "コリンク": "すやすや",
    "ルクシオ": "すやすや",
    "レントラー": "すやすや",
    "フワンテ": "うとうと",
    "フワライド": "うとうと",
    "ドンカラス": "うとうと",
    "ウソハチ": "ぐっすり",
    "マネネ": "ぐっすり",
    "ピンプク": "ぐっすり",
    "ミカルゲ": "うとうと",
    "リオル": "ぐっすり",
    "ルカリオ": "ぐっすり",
    "グレッグル": "うとうと",
    "ドクロッグ": "うとうと",
    "ユキカブリ": "ぐっすり",
    "ユキノオー": "ぐっすり",
    "マニューラ": "うとうと",
    "ジバコイル": "ぐっすり",
    "トゲキッス": "すやすや",
    "リーフィア": "うとうと",
    "グレイシア": "ぐっすり",
    "エルレイド": "ぐっすり",
    "クレセリア": "すやすや",
    "ダークライ": "うとうと",
    "ムンナ": "すやすや",
    "ムシャーナ": "すやすや",
    "イシズマイ": "うとうと",
    "イワパレス": "うとうと",
    "ワシボン": "ぐっすり",
    "ウォーグル": "ぐっすり",
    "チゴラス": "ぐっすり",
    "ガチゴラス": "ぐっすり",
    "ニンフィア": "すやすや",
    "デデンネ": "すやすや",
    "バケッチャ": "うとうと",
    "パンプジン": "うとうと",
    "オンバット": "うとうと",
    "オンバーン": "うとうと",
    "アゴジムシ": "うとうと",
    "デンヂムシ": "うとうと",
    "クワガノン": "うとうと",
    "アブリー": "すやすや",
    "アブリボン": "すやすや",
    "ヌイコグマ": "ぐっすり",
    "キテルグマ": "ぐっすり",
    "キュワワー": "すやすや",
    "トゲデマル": "ぐっすり",
    "ミミッキュ": "うとうと",
    "ジジーロン": "うとうと",
    "ウッウ": "ぐっすり",
    "エレズン": "ぐっすり",
    "ストリンダー": "うとうと",
    "ニャオハ": "うとうと",
    "ニャローテ": "うとうと",
    "マスカーニャ": "うとうと",
    "ホゲータ": "すやすや",
    "アチゲータ": "すやすや",
    "ラウドボーン": "うとうと",
    "クワッス": "ぐっすり",
    "ウェルカモ": "ぐっすり",
    "ウェーニバル": "ぐっすり",
    "パモ": "すやすや",
    "パモット": "すやすや",
    "パーモット": "すやすや",
    "アルクジラ": "ぐっすり",
    "ハルクジラ": "ぐっすり",
    "ドオー": "うとうと"
  }
}